plover_hjson_dictionary.py
plover_hjson_dictionary-0.0.2.dist-info/DESCRIPTION.rst
plover_hjson_dictionary-0.0.2.dist-info/METADATA
plover_hjson_dictionary-0.0.2.dist-info/RECORD
plover_hjson_dictionary-0.0.2.dist-info/WHEEL
plover_hjson_dictionary-0.0.2.dist-info/entry_points.txt
plover_hjson_dictionary-0.0.2.dist-info/metadata.json
plover_hjson_dictionary-0.0.2.dist-info/top_level.txt
plover_hjson_dictionary-0.0.2.dist-info/zip-safe
