Metadata-Version: 2.0
Name: plover-hjson-dictionary
Version: 0.0.2
Summary: Hjson dictionary support for Plover
Home-page: https://github.com/nsmarkop/plover_hjson_dictionary
Author: Nick Markopoulos
Author-email: nsmarkop@gmail.com
License: GNU General Public License v3 or later (GPLv3+)
Keywords: plover plover_plugin
Platform: UNKNOWN
Classifier: Development Status :: 4 - Beta
Classifier: Environment :: Plugins
Classifier: Intended Audience :: End Users/Desktop
Classifier: License :: OSI Approved :: GNU General Public License v3 or later (GPLv3+)
Classifier: Operating System :: OS Independent
Classifier: Programming Language :: Python :: 3
Classifier: Programming Language :: Python :: 3.6
Requires-Dist: plover (>=4.0.0.dev1)
Requires-Dist: hjson (>=3.0.1)
